spacecomx/cdk_organization_billing-alarm/__init__.py
spacecomx/cdk_organization_billing-alarm/py.typed
spacecomx/cdk_organization_billing-alarm/_jsii/__init__.py
spacecomx/cdk_organization_billing-alarm/_jsii/cdk-organization-billing-alarm@1.0.17.jsii.tgz
spacecomx.cdk_organization_billing_alarm-1.0.17.dist-info/LICENSE
spacecomx.cdk_organization_billing_alarm-1.0.17.dist-info/METADATA
spacecomx.cdk_organization_billing_alarm-1.0.17.dist-info/WHEEL
spacecomx.cdk_organization_billing_alarm-1.0.17.dist-info/top_level.txt
spacecomx.cdk_organization_billing_alarm-1.0.17.dist-info/RECORD
