Metadata-Version: 2.1
Name: spacecomx.cdk-organization-billing-alarm
Version: 1.0.17
Summary: Multi-account CDK construct to monitor estimated billing charges with alerts and notifications for a AWS Organization. It gives you the capability to monitor specific AWS Service charges, by a linked AWS account in a master/payer account
Home-page: https://github.com/spacecomx/cdk-organization-billing-alarm.git
Author: Wayne Gibson<wayne.gibson@spacecomx.com>
License: MIT
Project-URL: Source, https://github.com/spacecomx/cdk-organization-billing-alarm.git
Platform: UNKNOWN
Classifier: Intended Audience :: Developers
Classifier: Operating System :: OS Independent
Classifier: Programming Language :: JavaScript
Classifier: Programming Language :: Python :: 3 :: Only
Classifier: Programming Language :: Python :: 3.6
Classifier: Programming Language :: Python :: 3.7
Classifier: Programming Language :: Python :: 3.8
Classifier: Programming Language :: Python :: 3.9
Classifier: Typing :: Typed
Classifier: Development Status :: 5 - Production/Stable
Classifier: License :: OSI Approved
Requires-Python: >=3.6
License-File: LICENSE
Requires-Dist: aws-cdk.aws-secretsmanager (<2.0.0,>=1.125.0)
Requires-Dist: aws-cdk.aws-sns (<2.0.0,>=1.125.0)
Requires-Dist: aws-cdk.core (<2.0.0,>=1.125.0)
Requires-Dist: constructs (<4.0.0,>=3.2.27)
Requires-Dist: jsii (<2.0.0,>=1.35.0)
Requires-Dist: publication (>=0.0.3)
Requires-Dist: spacecomx.cdk-billing-alarm (<2.0.0,>=1.0.20)
